suthing/__init__.py
suthing/compare.py
suthing/decorate.py
suthing/file_handle.py
suthing/timer.py
suthing-0.5.0.dist-info/METADATA
suthing-0.5.0.dist-info/WHEEL
suthing-0.5.0.dist-info/licenses/LICENSE
suthing-0.5.0.dist-info/RECORD
