Metadata-Version: 2.4
Name: suthing
Version: 0.5.0
Summary: Small Useful Things : python package for convenient primitives
Project-URL: Homepage, https://github.com/growgraph/suthing
Author-email: Alexander Belikov <abelikov@gmail.com>
License-Expression: MIT
License-File: LICENSE
Keywords: suthing,tools
Classifier: License :: OSI Approved :: MIT License
Classifier: Programming Language :: Python
Classifier: Programming Language :: Python :: 3
Requires-Python: <4,>=3.10
Requires-Dist: dataclass-wizard<0.35,>=0.34.0
Requires-Dist: mkdocs-gen-files>=0.5.0
Requires-Dist: pandas<3,>=2.0.3
Requires-Dist: python-dotenv<2,>=1.0.0
Requires-Dist: pyyaml>=3.10
Requires-Dist: strenum>=0.4.15
